jupyter_security/__init__.py
jupyter_security/_version.py
jupyter_security/handlers.py
jupyter_security/tests/__init__.py
jupyter_security/tests/test_handlers.py
jupyter_security-0.0.2.data/data/etc/jupyter/jupyter_notebook_config.d/jupyter_security.json
jupyter_security-0.0.2.data/data/etc/jupyter/jupyter_server_config.d/jupyter_security.json
jupyter_security-0.0.2.data/data/share/jupyter/labextensions/@datalayer/jupyter-security/build_log.json
jupyter_security-0.0.2.data/data/share/jupyter/labextensions/@datalayer/jupyter-security/package.json
jupyter_security-0.0.2.data/data/share/jupyter/labextensions/@datalayer/jupyter-security/schemas/@datalayer/jupyter-admin/package.json.orig
jupyter_security-0.0.2.data/data/share/jupyter/labextensions/@datalayer/jupyter-security/schemas/@datalayer/jupyter-admin/plugin.json
jupyter_security-0.0.2.data/data/share/jupyter/labextensions/@datalayer/jupyter-security/static/lib_index_js.4348b810ae8dc12e002f.js
jupyter_security-0.0.2.data/data/share/jupyter/labextensions/@datalayer/jupyter-security/static/lib_index_js.4348b810ae8dc12e002f.js.map
jupyter_security-0.0.2.data/data/share/jupyter/labextensions/@datalayer/jupyter-security/static/remoteEntry.60045aa25abfdbe55e4f.js
jupyter_security-0.0.2.data/data/share/jupyter/labextensions/@datalayer/jupyter-security/static/remoteEntry.60045aa25abfdbe55e4f.js.map
jupyter_security-0.0.2.data/data/share/jupyter/labextensions/@datalayer/jupyter-security/static/style.js
jupyter_security-0.0.2.data/data/share/jupyter/labextensions/@datalayer/jupyter-security/static/style_index_js.09ea6e1de3ce833faf40.js
jupyter_security-0.0.2.data/data/share/jupyter/labextensions/@datalayer/jupyter-security/static/style_index_js.09ea6e1de3ce833faf40.js.map
jupyter_security-0.0.2.data/data/share/jupyter/labextensions/@datalayer/jupyter-security/static/vendors-node_modules_css-loader_dist_runtime_api_js-node_modules_css-loader_dist_runtime_cssW-72eba1.bac0ab4f283009af8f3d.js
jupyter_security-0.0.2.dist-info/METADATA
jupyter_security-0.0.2.dist-info/WHEEL
jupyter_security-0.0.2.dist-info/licenses/LICENSE
jupyter_security-0.0.2.dist-info/RECORD
